mepcheck/__init__.py
mepcheck/mepcheck.py
mepcheck/mepcheck_cli.py
mepcheck/savemeps.py
mepcheck-0.0.2.dist-info/DESCRIPTION.rst
mepcheck-0.0.2.dist-info/METADATA
mepcheck-0.0.2.dist-info/RECORD
mepcheck-0.0.2.dist-info/WHEEL
mepcheck-0.0.2.dist-info/metadata.json
mepcheck-0.0.2.dist-info/top_level.txt
