Metadata-Version: 2.0
Name: mepcheck
Version: 0.0.2
Summary: Retrieve voting data for all MEPs and return them in a structured way
Home-page: https://github.com/alanmarazzi/mepcheck
Author: Alan Marazzi
Author-email: alan.marazzi@gmail.com
License: MIT
Download-URL: https://github.com/alanmarazzi/mepcheck/archive/master.zip
Keywords: voting,data,mep
Platform: UNKNOWN
Classifier: Programming Language :: Python :: 3
Classifier: Programming Language :: Python :: 3.4
Classifier: Programming Language :: Python :: 3.5
Classifier: Programming Language :: Python :: 3.6
Requires-Dist: beautifulsoup4
Requires-Dist: prettytable
Requires-Dist: requests
